README.md
setup.py
RockPaperScissorsGame/__init__.py
RockPaperScissorsGame/game.py
RockPaperScissorsGame/player.py
RockPaperScissorsGame/players.py
RockPaperScissorsGame/utils.py
RockPaperScissorsGame.egg-info/PKG-INFO
RockPaperScissorsGame.egg-info/SOURCES.txt
RockPaperScissorsGame.egg-info/dependency_links.txt
RockPaperScissorsGame.egg-info/not-zip-safe
RockPaperScissorsGame.egg-info/top_level.txt