Metadata-Version: 1.0
Name: RockPaperScissorsGame
Version: 0.1
Summary: The classic game of Rock Paper Scissors
Home-page: UNKNOWN
Author: David Mixer
Author-email: UNKNOWN
License: UNKNOWN
Platform: UNKNOWN
